{"name":"Vue2基础","slug":"Vue2基础","count":7,"postlist":[{"title":"一. Vue简介","uid":"50e76213b8e48ed7ab8926d9188dc1c3","slug":"一. Vue简介","date":"2022-12-02T06:17:27.478Z","updated":"2022-12-02T06:21:22.904Z","comments":true,"path":"api/articles/一. Vue简介.json","keywords":null,"cover":null,"text":" 1 什么是Vue:::infoVue是一个动态构建用户界面的** 渐进式** JS框架. 遵循MVVM模式::: 构建用户界面: 将数据转换成界面 渐进式: 自底向上慢慢改进 简单应用: 当成jQuery的代替品 中型应用: 应用组件化, 重构某个(某些)页面 大型应用: 使用...","link":"","photos":[],"count_time":{"symbolsCount":348,"symbolsTime":"1 mins."},"categories":[{"name":"Vue","slug":"Vue","count":16,"path":"api/categories/Vue.json"}],"tags":[{"name":"Vue2基础","slug":"Vue2基础","count":7,"path":"api/tags/Vue2基础.json"}],"author":{"name":"团子","slug":"blog-author","avatar":"https://blog4xk-1309331490.cos.ap-nanjing.myqcloud.com/markdown/QQ%E5%9B%BE%E7%89%8720221205215218.jpg","link":"/","description":"处变不惊   安之若素","socials":{"github":"https://github.com/codbish","twitter":"","stackoverflow":"","wechat":"","qq":"","weibo":"","zhihu":"","csdn":"https://blog.csdn.net/bguihiub","juejin":"","customs":{}}}},{"title":"三. Vue实例","uid":"8f523ce4af9881778f9f63851115ecc9","slug":"三. Vue实例_new","date":"2022-12-02T07:45:14.541Z","updated":"2022-12-02T07:45:14.542Z","comments":true,"path":"api/articles/三. Vue实例_new.json","keywords":null,"cover":[],"text":" 1 属性和方法Vue 应用的核心就是 Vue 实例 , 一个基本的 Vue 实例包括如下图所示: new Vue(&#123; el: &#39;#app&#39;, data: &#123;&#125;, methods: &#123;&#125; &#125;) el: 表...","link":"","photos":[],"count_time":{"symbolsCount":"4.6k","symbolsTime":"4 mins."},"categories":[{"name":"Vue","slug":"Vue","count":16,"path":"api/categories/Vue.json"}],"tags":[{"name":"Vue2基础","slug":"Vue2基础","count":7,"path":"api/tags/Vue2基础.json"}],"author":{"name":"团子","slug":"blog-author","avatar":"https://blog4xk-1309331490.cos.ap-nanjing.myqcloud.com/markdown/QQ%E5%9B%BE%E7%89%8720221205215218.jpg","link":"/","description":"处变不惊   安之若素","socials":{"github":"https://github.com/codbish","twitter":"","stackoverflow":"","wechat":"","qq":"","weibo":"","zhihu":"","csdn":"https://blog.csdn.net/bguihiub","juejin":"","customs":{}}}},{"title":"二. Vue快速上手","uid":"f633b9b7ebaccaa57757f7c5003e83b0","slug":"二. Vue快速上手_new","date":"2022-12-02T07:21:33.958Z","updated":"2022-12-02T07:21:33.958Z","comments":true,"path":"api/articles/二. Vue快速上手_new.json","keywords":null,"cover":[],"text":" 1 搭建开发环境 1) 初始化使用如下指令初始化 npm init -y 发现在目录下会多一个文件package.json, 这个文件用来管理该项目使用了哪些包 2) 安装vue执行如下命令安装vue npm install vue@2 --save 以上命令可以简写为 npm...","link":"","photos":[],"count_time":{"symbolsCount":"2.1k","symbolsTime":"2 mins."},"categories":[{"name":"Vue","slug":"Vue","count":16,"path":"api/categories/Vue.json"}],"tags":[{"name":"Vue2基础","slug":"Vue2基础","count":7,"path":"api/tags/Vue2基础.json"}],"author":{"name":"团子","slug":"blog-author","avatar":"https://blog4xk-1309331490.cos.ap-nanjing.myqcloud.com/markdown/QQ%E5%9B%BE%E7%89%8720221205215218.jpg","link":"/","description":"处变不惊   安之若素","socials":{"github":"https://github.com/codbish","twitter":"","stackoverflow":"","wechat":"","qq":"","weibo":"","zhihu":"","csdn":"https://blog.csdn.net/bguihiub","juejin":"","customs":{}}}},{"title":"五. Vue模板语法","uid":"2bf64ee2a2c6d7942433bae3817e775f","slug":"五. Vue模板语法_new","date":"2022-12-02T08:05:49.083Z","updated":"2022-12-02T08:05:49.084Z","comments":true,"path":"api/articles/五. Vue模板语法_new.json","keywords":null,"cover":[],"text":" 1 简介 什么是模板 :::info由Vue解析的HTML字符串::: 什么是模板语法 :::info在模板字符串中, 具有特殊意义的语法::: 2 分类:::info模板语法分为 插值语法 指令语法::: 1) 插值语法 语法 在&#123;&#123;&#125;&#125...","link":"","photos":[],"count_time":{"symbolsCount":"22k","symbolsTime":"20 mins."},"categories":[{"name":"Vue","slug":"Vue","count":16,"path":"api/categories/Vue.json"}],"tags":[{"name":"Vue2基础","slug":"Vue2基础","count":7,"path":"api/tags/Vue2基础.json"}],"author":{"name":"团子","slug":"blog-author","avatar":"https://blog4xk-1309331490.cos.ap-nanjing.myqcloud.com/markdown/QQ%E5%9B%BE%E7%89%8720221205215218.jpg","link":"/","description":"处变不惊   安之若素","socials":{"github":"https://github.com/codbish","twitter":"","stackoverflow":"","wechat":"","qq":"","weibo":"","zhihu":"","csdn":"https://blog.csdn.net/bguihiub","juejin":"","customs":{}}}},{"title":"任务","uid":"c167393a4acf0fefa10f0093679620ef","slug":"任务","date":"2022-12-02T10:42:29.611Z","updated":"2022-12-02T10:51:45.434Z","comments":true,"path":"api/articles/任务.json","keywords":null,"cover":null,"text":"12月3号 组件通信复习，看视频+看文档+总结","link":"","photos":[],"count_time":{"symbolsCount":23,"symbolsTime":"1 mins."},"categories":[{"name":"梳理","slug":"梳理","count":1,"path":"api/categories/梳理.json"}],"tags":[{"name":"Vue2基础","slug":"Vue2基础","count":7,"path":"api/tags/Vue2基础.json"}],"author":{"name":"团子","slug":"blog-author","avatar":"https://blog4xk-1309331490.cos.ap-nanjing.myqcloud.com/markdown/QQ%E5%9B%BE%E7%89%8720221205215218.jpg","link":"/","description":"处变不惊   安之若素","socials":{"github":"https://github.com/codbish","twitter":"","stackoverflow":"","wechat":"","qq":"","weibo":"","zhihu":"","csdn":"https://blog.csdn.net/bguihiub","juejin":"","customs":{}}},"feature":true},{"title":"六. 计算属性与侦听器","uid":"4277aac2cb081b743e86fc465443e28f","slug":"六. 计算属性与侦听器_new","date":"2022-12-02T09:43:08.004Z","updated":"2022-12-02T09:43:08.005Z","comments":true,"path":"api/articles/六. 计算属性与侦听器_new.json","keywords":null,"cover":[],"text":" 1 计算属性 1) 什么是计算属性:::info计算属性就是基于现有属性计算后的属性::: 2) 计算属性的作用计算属性用于对原始数据的再次加工 3) 案例:::warning需求实现如下效果::: 使用表达式实现&lt;!DOCTYPE html&gt; &lt;html l...","link":"","photos":[],"count_time":{"symbolsCount":"8.5k","symbolsTime":"8 mins."},"categories":[{"name":"Vue","slug":"Vue","count":16,"path":"api/categories/Vue.json"}],"tags":[{"name":"Vue2基础","slug":"Vue2基础","count":7,"path":"api/tags/Vue2基础.json"}],"author":{"name":"团子","slug":"blog-author","avatar":"https://blog4xk-1309331490.cos.ap-nanjing.myqcloud.com/markdown/QQ%E5%9B%BE%E7%89%8720221205215218.jpg","link":"/","description":"处变不惊   安之若素","socials":{"github":"https://github.com/codbish","twitter":"","stackoverflow":"","wechat":"","qq":"","weibo":"","zhihu":"","csdn":"https://blog.csdn.net/bguihiub","juejin":"","customs":{}}}},{"title":"四. MVVM模型","uid":"038e2b47ac293a17a4e188acb02dbb61","slug":"四. MVVM模型_new","date":"2022-12-02T07:56:03.005Z","updated":"2022-12-02T07:56:03.006Z","comments":true,"path":"api/articles/四. MVVM模型_new.json","keywords":null,"cover":[],"text":" 1 什么是MVVM模型:::infoMVVM由 Model(数据模型) View(视图) 和 VM(ViewModel) 组成::: 1) 核心思想实现 数据 与 视图 的 双向绑定 各自的作用 Model(数据模型): 操作数据 View(视图): 显示数据 VM: 模型与视...","link":"","photos":[],"count_time":{"symbolsCount":"1.7k","symbolsTime":"2 mins."},"categories":[{"name":"Vue","slug":"Vue","count":16,"path":"api/categories/Vue.json"}],"tags":[{"name":"Vue2基础","slug":"Vue2基础","count":7,"path":"api/tags/Vue2基础.json"}],"author":{"name":"团子","slug":"blog-author","avatar":"https://blog4xk-1309331490.cos.ap-nanjing.myqcloud.com/markdown/QQ%E5%9B%BE%E7%89%8720221205215218.jpg","link":"/","description":"处变不惊   安之若素","socials":{"github":"https://github.com/codbish","twitter":"","stackoverflow":"","wechat":"","qq":"","weibo":"","zhihu":"","csdn":"https://blog.csdn.net/bguihiub","juejin":"","customs":{}}}}]}